README.rst
setup.py
transencoding.py
transencoding.egg-info/PKG-INFO
transencoding.egg-info/SOURCES.txt
transencoding.egg-info/dependency_links.txt
transencoding.egg-info/entry_points.txt
transencoding.egg-info/requires.txt
transencoding.egg-info/top_level.txt