Metadata-Version: 1.1
Name: transencoding
Version: 0.1.0
Summary: Convert encoding of given file from one encoding to another.
Home-page: https://github.com/appstore-zencore/transencoding
Author: zencore
Author-email: dobetter@zencore.cn
License: MIT
Keywords: transencoding
Platform: UNKNOWN
Classifier: Development Status :: 5 - Production/Stable
Classifier: Intended Audience :: Developers
Classifier: Topic :: Software Development :: Libraries :: Python Modules
Classifier: License :: OSI Approved :: MIT License
Classifier: Programming Language :: Python :: 3
Classifier: Programming Language :: Python :: 3 :: Only
Requires: click
